translation_helps/__init__.py
translation_helps/adapters.py
translation_helps/client.py
translation_helps/prompts.py
translation_helps/types.py
translation_helps_mcp_client-1.5.0.dist-info/licenses/LICENSE
translation_helps_mcp_client-1.5.0.dist-info/METADATA
translation_helps_mcp_client-1.5.0.dist-info/WHEEL
translation_helps_mcp_client-1.5.0.dist-info/top_level.txt
translation_helps_mcp_client-1.5.0.dist-info/RECORD
