Metadata-Version: 2.4
Name: translation-helps-mcp-client
Version: 1.5.0
Summary: Official Python client SDK for Translation Helps MCP Server
Author: unfoldingWord
License: MIT
Project-URL: Homepage, https://github.com/unfoldingWord/translation-helps-mcp
Project-URL: Documentation, https://tc-helps.mcp.servant.bible
Project-URL: Repository, https://github.com/unfoldingWord/translation-helps-mcp
Keywords: translation,bible,mcp,model-context-protocol,sdk,client,python
Classifier: Development Status :: 4 - Beta
Classifier: Intended Audience :: Developers
Classifier: License :: OSI Approved :: MIT License
Classifier: Programming Language :: Python :: 3
Classifier: Programming Language :: Python :: 3.8
Classifier: Programming Language :: Python :: 3.9
Classifier: Programming Language :: Python :: 3.10
Classifier: Programming Language :: Python :: 3.11
Classifier: Programming Language :: Python :: 3.12
Requires-Python: >=3.8
License-File: LICENSE
Requires-Dist: httpx>=0.24.0
Provides-Extra: dev
Requires-Dist: pytest>=7.0.0; extra == "dev"
Requires-Dist: pytest-asyncio>=0.21.0; extra == "dev"
Requires-Dist: black>=23.0.0; extra == "dev"
Requires-Dist: mypy>=1.0.0; extra == "dev"
Dynamic: license-file
